{"classifier":{"classFeatures":{"about page":{"0":2,"1":3,"2":3,"3":2,"4":2},"home page":{"0":4,"5":2,"6":2,"7":2,"8":2,"9":2},"todo page":{"0":2,"10":3}},"classTotals":{"about page":6,"home page":6,"todo page":3},"totalExamples":13,"smoothing":1},"docs":[{"label":"about page","text":["page"]},{"label":"about page","text":["us"]},{"label":"about page","text":["contact","us"]},{"label":"about page","text":["question"]},{"label":"about page","text":["contact","support"]},{"label":"home page","text":["home","page"]},{"label":"home page","text":["land","page"]},{"label":"home page","text":["sign"]},{"label":"home page","text":["log"]},{"label":"home page","text":["main","page"]},{"label":"todo page","text":["todo","page"]},{"label":"todo page","text":["todo"]}],"features":{"page":1,"us":1,"contact":1,"question":1,"support":1,"home":1,"land":1,"sign":1,"log":1,"main":1,"todo":1},"stemmer":{},"lastAdded":12,"events":{"domain":null,"_events":{}}}